mlflow_mage/__init__.py
mlflow_mage/mlflow_saver.py
mlflow_mage/py.typed
mlflow_mage/tags.py
mlflow_mage-0.1.0.dist-info/METADATA
mlflow_mage-0.1.0.dist-info/WHEEL
mlflow_mage-0.1.0.dist-info/RECORD
