Metadata-Version: 2.4
Name: mlflow-mage
Version: 0.1.0
Summary: MLFlow mage is a wrapper for MLFlow to allow for better logging capabilites inside Mage AI.
Author-email: Jarcau Stefan-Cristian <stefan.jarcau@siemens.com>
Requires-Python: >=3.10
Requires-Dist: boto3>=1.39.6
Requires-Dist: mlflow>=3.1.1
